assets/logo.svg
leptonai/__init__.py
leptonai/_version.py
leptonai/client.py
leptonai/config.py
leptonai/kv.py
leptonai/objectstore.py
leptonai/queue.py
leptonai/registry.py
leptonai/_internal/__init__.py
leptonai/_internal/client_utils.py
leptonai/_internal/db.py
leptonai/_internal/logging.py
leptonai/_internal/tests/test_logging.py
leptonai/api/__init__.py
leptonai/api/v0/__init__.py
leptonai/api/v0/connection.py
leptonai/api/v0/deployment.py
leptonai/api/v0/job.py
leptonai/api/v0/kv.py
leptonai/api/v0/nodegroup.py
leptonai/api/v0/objectstore.py
leptonai/api/v0/photon.py
leptonai/api/v0/queue.py
leptonai/api/v0/secret.py
leptonai/api/v0/storage.py
leptonai/api/v0/types.py
leptonai/api/v0/util.py
leptonai/api/v0/workspace.py
leptonai/api/v1/__init__.py
leptonai/api/v1/api_resource.py
leptonai/api/v1/client.py
leptonai/api/v1/dedicated_node_groups.py
leptonai/api/v1/deployment.py
leptonai/api/v1/events.py
leptonai/api/v1/healthcheck.py
leptonai/api/v1/ingress.py
leptonai/api/v1/job.py
leptonai/api/v1/kv.py
leptonai/api/v1/log.py
leptonai/api/v1/monitoring.py
leptonai/api/v1/object_storage.py
leptonai/api/v1/photon.py
leptonai/api/v1/pod.py
leptonai/api/v1/queue.py
leptonai/api/v1/raycluster.py
leptonai/api/v1/readiness.py
leptonai/api/v1/replica.py
leptonai/api/v1/secret.py
leptonai/api/v1/storage.py
leptonai/api/v1/template.py
leptonai/api/v1/utils.py
leptonai/api/v1/workspace_record.py
leptonai/api/v1/types/__init__.py
leptonai/api/v1/types/affinity.py
leptonai/api/v1/types/auth.py
leptonai/api/v1/types/common.py
leptonai/api/v1/types/dedicated_node_group.py
leptonai/api/v1/types/deployment.py
leptonai/api/v1/types/events.py
leptonai/api/v1/types/ingress.py
leptonai/api/v1/types/job.py
leptonai/api/v1/types/kv.py
leptonai/api/v1/types/object_storage.py
leptonai/api/v1/types/photon.py
leptonai/api/v1/types/quota.py
leptonai/api/v1/types/raycluster.py
leptonai/api/v1/types/readiness.py
leptonai/api/v1/types/replica.py
leptonai/api/v1/types/secret.py
leptonai-0.27.0.dist-info/licenses/LICENSE
leptonai-0.27.0.dist-info/licenses/NOTICE
leptonai-0.27.0.dist-info/METADATA
leptonai-0.27.0.dist-info/WHEEL
leptonai-0.27.0.dist-info/entry_points.txt
leptonai-0.27.0.dist-info/top_level.txt
leptonai-0.27.0.dist-info/RECORD
