Metadata-Version: 2.4
Name: leptonai
Version: 0.27.0
Summary: Lepton AI Platform
Author-email: "Lepton AI Inc." <dev@lepton.ai>
Project-URL: Homepage, https://lepton.ai
Requires-Python: <3.14,>=3.9
License-File: LICENSE
License-File: NOTICE
Requires-Dist: anyio<=4.9.0,>=3.7.0
Requires-Dist: click
Requires-Dist: cloudpickle==3.0.0
Requires-Dist: contextlib2
Requires-Dist: exceptiongroup
Requires-Dist: fastapi
Requires-Dist: httpx[http2]==0.27.2
Requires-Dist: prometheus-fastapi-instrumentator==7.0.0
Requires-Dist: rich
Requires-Dist: typing-extensions
Requires-Dist: uvicorn>=0.22.0
Requires-Dist: loguru
Requires-Dist: requests
Requires-Dist: pydantic!=2.1.0
Requires-Dist: python-multipart
Requires-Dist: pillow
Requires-Dist: pyyaml
Requires-Dist: huggingface_hub
Requires-Dist: ledoc-ui
Requires-Dist: ray[default]
Provides-Extra: lint
Requires-Dist: black==23.12.0; extra == "lint"
Requires-Dist: ruff==0.5.7; extra == "lint"
Provides-Extra: test
Requires-Dist: pytest; extra == "test"
Requires-Dist: pytest-cov; extra == "test"
Requires-Dist: responses; extra == "test"
Requires-Dist: respx; extra == "test"
Provides-Extra: runtime
Requires-Dist: accelerate; extra == "runtime"
Requires-Dist: huggingface_hub; extra == "runtime"
Requires-Dist: diffusers>=0.27.0; extra == "runtime"
Requires-Dist: sentence-transformers>=2.3.0; extra == "runtime"
Requires-Dist: torch; extra == "runtime"
Requires-Dist: transformers==4.46.3; extra == "runtime"
Dynamic: license-file
